yhttp/markdown/__init__.py
yhttp/markdown/decorator.py
yhttp/markdown/markdown.py
yhttp/markdown/server.py
yhttp/markdown/toc.py
yhttp/markdown/defaultmetadata/android-chrome-192x192.png
yhttp/markdown/defaultmetadata/android-chrome-512x512.png
yhttp/markdown/defaultmetadata/apple-touch-icon.png
yhttp/markdown/defaultmetadata/favicon-16x16.png
yhttp/markdown/defaultmetadata/favicon-32x32.png
yhttp/markdown/defaultmetadata/favicon.ico
yhttp/markdown/defaultmetadata/logo.svg
yhttp/markdown/static/index.js
yhttp/markdown/static/mermaid.esm.min.mjs
yhttp/markdown/static/highlight/autumn.css
yhttp/markdown/static/highlight/borland.css
yhttp/markdown/static/highlight/bw.css
yhttp/markdown/static/highlight/colorful.css
yhttp/markdown/static/highlight/default.css
yhttp/markdown/static/highlight/emacs.css
yhttp/markdown/static/highlight/friendly.css
yhttp/markdown/static/highlight/fruity.css
yhttp/markdown/static/highlight/manni.css
yhttp/markdown/static/highlight/monokai.css
yhttp/markdown/static/highlight/murphy.css
yhttp/markdown/static/highlight/native.css
yhttp/markdown/static/highlight/pastie.css
yhttp/markdown/static/highlight/perldoc.css
yhttp/markdown/static/highlight/tango.css
yhttp/markdown/static/highlight/trac.css
yhttp/markdown/static/highlight/vim.css
yhttp/markdown/static/highlight/vs.css
yhttp/markdown/styles/extras.sass
yhttp/markdown/styles/index.sass
yhttp/markdown/styles/layout.sass
yhttp/markdown/styles/reset.sass
yhttp/markdown/styles/theme.sass
yhttp/markdown/styles/variables.sass
yhttp/markdown/templates/default.mako
yhttp/markdown/templates/icons.svg
yhttp/markdown/templates/master.mako
yhttp/markdown/templates/notfound.mako
yhttp_markdown-2.0.0.dist-info/licenses/LICENSE
yhttp_markdown-2.0.0.dist-info/METADATA
yhttp_markdown-2.0.0.dist-info/WHEEL
yhttp_markdown-2.0.0.dist-info/entry_points.txt
yhttp_markdown-2.0.0.dist-info/top_level.txt
yhttp_markdown-2.0.0.dist-info/RECORD
