Metadata-Version: 2.4
Name: yhttp-markdown
Version: 2.0.0
Summary: Markdown to HTML coverter and server with yhttp.
Home-page: https://github.com/yhttp/markdown
Author: Vahid Mardani
License: APLv1
Classifier: Environment :: Console
Classifier: Environment :: Web Environment
Classifier: Intended Audience :: Developers
Classifier: Natural Language :: English
Classifier: Development Status :: 5 - Production/Stable
Classifier: License :: Other/Proprietary License
Classifier: Operating System :: OS Independent
Classifier: Programming Language :: Python :: 3.6
Classifier: Topic :: Software Development
Classifier: Topic :: Internet :: WWW/HTTP
Classifier: Topic :: Internet :: WWW/HTTP :: Dynamic Content
Classifier: Topic :: Internet :: WWW/HTTP :: WSGI :: Application
Classifier: Topic :: Software Development :: Libraries
Classifier: Topic :: Software Development :: Libraries :: Python Modules
License-File: LICENSE
Requires-Dist: yhttp<8,>=7.0.1
Requires-Dist: pymlconf
Requires-Dist: easycli
Requires-Dist: markdown2
Requires-Dist: mako
Requires-Dist: pygments
Requires-Dist: libsass
Dynamic: author
Dynamic: classifier
Dynamic: description
Dynamic: description-content-type
Dynamic: home-page
Dynamic: license
Dynamic: license-file
Dynamic: requires-dist
Dynamic: summary
